README.rst
pyproject.toml
setup.cfg
setup.py
src/hawkins/__init__.py
src/hawkins/_version.py
src/hawkins/ai.py
src/hawkins/chessboard.py
src/hawkins/gamelists.py
src/hawkins/generator.py
src/hawkins/heuristic.py
src/hawkins/movements.py
src/hawkins/rules.py
src/hawkins/util.py
src/hawkins.egg-info/PKG-INFO
src/hawkins.egg-info/SOURCES.txt
src/hawkins.egg-info/dependency_links.txt
src/hawkins.egg-info/not-zip-safe
src/hawkins.egg-info/requires.txt
src/hawkins.egg-info/top_level.txt